py3_requests/__init__.py
py3_requests-1.1.8.dist-info/LICENSE
py3_requests-1.1.8.dist-info/METADATA
py3_requests-1.1.8.dist-info/WHEEL
py3_requests-1.1.8.dist-info/top_level.txt
py3_requests-1.1.8.dist-info/RECORD
