Metadata-Version: 2.1
Name: py3-requests
Version: 1.1.8
Summary: The Python3 Requests Library Developed By Guolei
Home-page: https://github.com/guolei19850528/py3_requests
Author: guolei
Author-email: 174000902@qq.com
License: MIT
Requires-Python: >=3.0
License-File: LICENSE
Requires-Dist: requests
Requires-Dist: addict
Requires-Dist: jsonschema
Requires-Dist: retrying
Requires-Dist: xmltodict
Requires-Dist: beautifulsoup4
Requires-Dist: lxml
Requires-Dist: html5lib
Requires-Dist: setuptools
Requires-Dist: wheel
